broompy
