Metadata-Version: 2.1
Name: broompy
Version: 2.1.3
Summary: Data cleaning tool for Python
Home-page: https://github.com/juanduranc/broompy
Author: Juan Duran
Author-email: juan.duran.info@gmail.com
License: MIT
Platform: UNKNOWN
Classifier: License :: OSI Approved :: MIT License
Classifier: Programming Language :: Python
Classifier: Programming Language :: Python :: 3
Classifier: Programming Language :: Python :: 3.6
Classifier: Programming Language :: Python :: Implementation :: CPython
Classifier: Programming Language :: Python :: Implementation :: PyPy
Requires-Python: >=3.6.0
